messh/__init__.py
messh/cli.py
messh/config.py
messh/ssh.py
messh-1.2.0.dist-info/LICENSE
messh-1.2.0.dist-info/METADATA
messh-1.2.0.dist-info/WHEEL
messh-1.2.0.dist-info/entry_points.txt
messh-1.2.0.dist-info/top_level.txt
messh-1.2.0.dist-info/RECORD
