Metadata-Version: 2.1
Name: messh
Version: 1.2.0
Summary: A useful SSH configuration manager.
Home-page: https://github.com/abersheeran/messh
Author: Aber Sheeran
Author-email: abersheeran@qq.com
License: MIT
Platform: UNKNOWN
Classifier: License :: OSI Approved :: MIT License
Classifier: Programming Language :: Python :: 3.6
Classifier: Programming Language :: Python :: Implementation :: CPython
Classifier: Programming Language :: Python :: Implementation :: PyPy
Requires-Python: >=3.6.0
Requires-Dist: colorama
Requires-Dist: click
Requires-Dist: paramiko
Requires-Dist: pysftp
